odoo8_addon_base_iso3166-8.0.1.0.1-py2.7-nspkg.pth
odoo8_addon_base_iso3166-8.0.1.0.1.dist-info/METADATA
odoo8_addon_base_iso3166-8.0.1.0.1.dist-info/RECORD
odoo8_addon_base_iso3166-8.0.1.0.1.dist-info/WHEEL
odoo8_addon_base_iso3166-8.0.1.0.1.dist-info/namespace_packages.txt
odoo8_addon_base_iso3166-8.0.1.0.1.dist-info/top_level.txt
odoo_addons/base_iso3166/README.rst
odoo_addons/base_iso3166/__init__.py
odoo_addons/base_iso3166/__openerp__.py
odoo_addons/base_iso3166/models/__init__.py
odoo_addons/base_iso3166/models/res_country.py
odoo_addons/base_iso3166/static/description/icon.png
odoo_addons/base_iso3166/static/description/icon.svg
odoo_addons/base_iso3166/views/country_view.xml
