Metadata-Version: 2.1
Name: odoo8-addon-base-iso3166
Version: 8.0.1.0.1
Summary: ISO 3166
Home-page: https://odoo-community.org
Author: Tecnativa, Creu Blanca, Odoo Community Association (OCA)
Author-email: support@odoo-community.org
License: AGPL-3
Platform: UNKNOWN
Classifier: Programming Language :: Python
Classifier: Framework :: Odoo
Classifier: License :: OSI Approved :: GNU Affero General Public License v3
Requires-Python: ~=2.7
Requires-Dist: odoo (<9.0a,>=8.0a)
Requires-Dist: pycountry
